stagehand/__init__.py
stagehand/agent.py
stagehand/base.py
stagehand/client.py
stagehand/config.py
stagehand/context.py
stagehand/domScripts.js
stagehand/page.py
stagehand/schemas.py
stagehand/utils.py
stagehand_py-0.3.10.dist-info/METADATA
stagehand_py-0.3.10.dist-info/WHEEL
stagehand_py-0.3.10.dist-info/top_level.txt
stagehand_py-0.3.10.dist-info/RECORD
