Metadata-Version: 2.4
Name: stagehand-py
Version: 0.3.10
Summary: Python SDK for Stagehand
Author-email: "Browserbase, Inc." <support@browserbase.com>
License: MIT
Project-URL: Homepage, https://github.com/browserbase/stagehand-python
Project-URL: Repository, https://github.com/browserbase/stagehand-python
Classifier: Programming Language :: Python :: 3
Classifier: License :: OSI Approved :: MIT License
Classifier: Operating System :: OS Independent
Requires-Python: >=3.9
Requires-Dist: httpx>=0.24.0
Requires-Dist: python-dotenv>=1.0.0
Requires-Dist: pydantic>=1.10.0
Requires-Dist: playwright>=1.42.1
Requires-Dist: requests>=2.31.0
Requires-Dist: browserbase>=1.4.0
Provides-Extra: dev
Requires-Dist: pytest>=7.3.1; extra == "dev"
Requires-Dist: pytest-asyncio>=0.21.0; extra == "dev"
Requires-Dist: pytest-mock>=3.10.0; extra == "dev"
Requires-Dist: pytest-cov>=4.1.0; extra == "dev"
Requires-Dist: black>=23.3.0; extra == "dev"
Requires-Dist: isort>=5.12.0; extra == "dev"
Requires-Dist: mypy>=1.3.0; extra == "dev"
Requires-Dist: ruff; extra == "dev"
Requires-Dist: rich; extra == "dev"
